README.md
setup.cfg
setup.py
vesync/__init__.py
vesync/api.py
vesync.egg-info/PKG-INFO
vesync.egg-info/SOURCES.txt
vesync.egg-info/dependency_links.txt
vesync.egg-info/top_level.txt