Metadata-Version: 1.1
Name: vesync
Version: 1.0.1
Summary: VeSync API wrapper.
Home-page: https://github.com/tylergets/python-vesync/
Author: tylergets
Author-email: tylergetsay@gmail.com
License: MIT
Platform: UNKNOWN
Classifier: License :: OSI Approved :: MIT License
Classifier: Operating System :: OS Independent
Classifier: Programming Language :: Python :: 3
